{
  "type": "query_catalog_with_filters",
  "label": "Query Catalog (Filtered)",
  "description": "Send a catalog request with multiple filter expressions to narrow results.",
  "params": [
    { "name": "service", "type": "service_ref", "required": true, "description": "EDC connector service to query" },
    { "name": "counter_party_address", "type": "string", "required": true, "description": "DSP endpoint of the counter-party connector" },
    { "name": "filters", "type": "filter_expression_list", "required": false, "description": "Filter expressions to narrow catalog results" }
  ],
  "outputs": [
    {
      "name": "catalog",
      "class": "catalog",
      "description": "The full catalog response",
      "schema": {
        "type": "object",
        "properties": {
          "@id": { "type": "string", "description": "Catalog ID" },
          "datasets": {
            "type": "array",
            "items": {
              "type": "object",
              "properties": {
                "@id": { "type": "string", "description": "Dataset/offer ID" },
                "hasPolicy": { "type": "object", "description": "ODRL policy" },
                "distribution": { "type": "array", "description": "Data distribution formats" }
              }
            }
          }
        }
      },
      "example": {
        "@id": "catalog-123",
        "datasets": [
          { "@id": "offer-abc", "hasPolicy": { "@id": "policy-1" }, "distribution": [] }
        ]
      }
    },
    {
      "name": "datasets",
      "class": "datasets",
      "description": "Array of datasets (offers) in the catalog",
      "schema": {
        "type": "array",
        "items": {
          "type": "object",
          "properties": {
            "@id": { "type": "string", "description": "Dataset/offer ID" },
            "hasPolicy": { "type": "object", "description": "ODRL policy" },
            "distribution": { "type": "array", "description": "Data distribution formats" }
          }
        }
      },
      "example": [
        { "@id": "offer-abc", "hasPolicy": { "@id": "policy-1" }, "distribution": [] }
      ]
    }
  ]
}
